novatrace/__init__.py
novatrace/novatrace.py
novatrace/system_info.py
novatrace/api/__init__.py
novatrace/api/api.py
novatrace/backend/__init__.py
novatrace/backend/docker_manager.py
novatrace/backend/registry.py
novatrace/backend/utils.py
novatrace/components/__init__.py
novatrace/connect/__init__.py
novatrace/database/__init__.py
novatrace/database/init_db.py
novatrace/database/model.py
novatrace/system/__init__.py
novatrace/system/metrics_collector.py
novatrace/system/system.py
novatrace/web_interface/Dockerfile
novatrace/web_interface/README.md
novatrace/web_interface/docker-entrypoint.sh
novatrace/web_interface/index.html
novatrace/web_interface/nginx.conf
novatrace/web_interface/package-lock.json
novatrace/web_interface/package.json
novatrace/web_interface/postcss.config.js
novatrace/web_interface/tailwind.config.js
novatrace/web_interface/vite.config.js
novatrace/web_interface/public/favicon.ico
novatrace/web_interface/public/novatrace.png
novatrace/web_interface/src/App.jsx
novatrace/web_interface/src/index.css
novatrace/web_interface/src/main.jsx
novatrace/web_interface/src/components/JSONFormatter.jsx
novatrace/web_interface/src/components/Layout.jsx
novatrace/web_interface/src/components/Login.jsx
novatrace/web_interface/src/components/MetricCard.jsx
novatrace/web_interface/src/components/RecentProjects.jsx
novatrace/web_interface/src/components/SystemChart.jsx
novatrace/web_interface/src/contexts/AuthContext.jsx
novatrace/web_interface/src/hooks/useProjects.js
novatrace/web_interface/src/hooks/useSystem.js
novatrace/web_interface/src/pages/Cost.jsx
novatrace/web_interface/src/pages/Dashboard.jsx
novatrace/web_interface/src/pages/Docs.jsx
novatrace/web_interface/src/pages/Projects.jsx
novatrace/web_interface/src/pages/Settings.jsx
novatrace/web_interface/src/pages/Traces.jsx
novatrace/web_interface/src/pages/Traces_fixed.jsx
novatrace/web_interface/src/pages/Usage.jsx
novatrace/web_interface/src/services/api.js
novatrace-1.3.5.dist-info/licenses/LICENSE
novatrace-1.3.5.dist-info/METADATA
novatrace-1.3.5.dist-info/WHEEL
novatrace-1.3.5.dist-info/top_level.txt
novatrace-1.3.5.dist-info/RECORD
