Metadata-Version: 2.4
Name: novatrace
Version: 1.3.5
Summary: A package to facilitate the traceability and management of LLM/Agent projects.
Author-email: Alexi Marin <novatrace.contact@gmail.com>
License-Expression: MIT
Requires-Python: >=3.12
License-File: LICENSE
Requires-Dist: sqlalchemy>=1.4
Requires-Dist: python-decouple
Requires-Dist: pytz
Requires-Dist: requests
Requires-Dist: reflex
Requires-Dist: fastapi>=0.116.1
Requires-Dist: bcrypt
Requires-Dist: psutil
Requires-Dist: pyjwt
Dynamic: license-file
